{
  "servers": {
    "astro-docs": {
      "type": "stdio",
      "command": "bunx",
      "args": ["-y", "mcp-remote", "https://mcp.docs.astro.build/mcp"]
    },
    "filesystem": {
      "type": "stdio",
      "command": "bunx",
      "args": ["-y", "@modelcontextprotocol/server-filesystem", "/workspaces"]
    },
    "typescript-lsp": {
      "type": "stdio",
      "command": "bunx",
      "args": ["-y", "@mizchi/lsmcp"]
    },
    "tailwindcss": {
      "type": "stdio",
      "command": "bunx",
      "args": ["-y", "tailwindcss-mcp-server"]
    },
    "bun-runtime": {
      "type": "stdio",
      "command": "bunx",
      "args": ["-y", "mcp-bun@latest"],
      "env": {
        "DISABLE_NOTIFICATIONS": "true"
      }
    },
    "context7": {
      "type": "stdio",
      "command": "bunx",
      "args": ["-y", "@upstash/context7-mcp@latest"]
    },
    "sequential-thinking": {
      "type": "stdio",
      "command": "bunx",
      "args": ["-y", "@modelcontextprotocol/server-sequential-thinking"]
    },
    "memory": {
      "type": "stdio",
      "command": "bunx",
      "args": ["-y", "@modelcontextprotocol/server-memory"]
    },
    // "github": {
    //   "type": "stdio",
    //   "command": "bunx",
    //   "args": ["-y", "@modelcontextprotocol/server-github"],
    //   "env": {
    //     "GITHUB_PERSONAL_ACCESS_TOKEN": "YOUR_TOKEN_HERE"
    //   }
    // },
    "playwright": {
      "type": "stdio",
      "command": "bunx",
      "args": ["@playwright/mcp@latest"]
    }
  }
}